helpers/__init__.py
mlModelSaver/__init__.py
mlModelSaver-1.0.33.dist-info/LICENSE
mlModelSaver-1.0.33.dist-info/METADATA
mlModelSaver-1.0.33.dist-info/WHEEL
mlModelSaver-1.0.33.dist-info/top_level.txt
mlModelSaver-1.0.33.dist-info/RECORD
