Metadata-Version: 2.1
Name: mlModelSaver
Version: 1.0.33
Summary: Make life easier for saving and serving ML models
Home-page: https://github.com/smartdev-ca/mlModelSaver
Author: Jason Jafari
Author-email: me@jasonjafari.com
Project-URL: Documentation, https://github.com/smartdev-ca/mlModelSaver/blob/main/DOCS.md
Project-URL: Source, https://github.com/smartdev-ca/mlModelSaver
Project-URL: Tracker, https://github.com/smartdev-ca/mlModelSaver/issues
Keywords: machine learning model saving serving
Classifier: Development Status :: 5 - Production/Stable
Classifier: Intended Audience :: Developers
Classifier: Intended Audience :: Science/Research
Classifier: Topic :: Software Development :: Libraries :: Python Modules
Classifier: Topic :: Scientific/Engineering :: Artificial Intelligence
Classifier: License :: OSI Approved :: MIT License
Classifier: Programming Language :: Python :: 3.12
License-File: LICENSE
Requires-Dist: numpy >=1.26.4
Requires-Dist: pandas >=2.2.2
Requires-Dist: scikit-learn >=1.5.0
Requires-Dist: statsmodels >=0.14.2
Requires-Dist: matplotlib >=3.9.0
Requires-Dist: dill >=0.3.8
